pyhbs/__init__.py
pyhbs/boot.py
pyhbs/builder.py
pyhbs/grammar.py
pyhbs/hbs_compiler.py
pyhbs/runtime.py
pyhbs/template.py
pyhbs-0.1.3.dist-info/LICENSE.txt
pyhbs-0.1.3.dist-info/METADATA
pyhbs-0.1.3.dist-info/RECORD
pyhbs-0.1.3.dist-info/WHEEL
pyhbs-0.1.3.dist-info/top_level.txt
