Metadata-Version: 2.1
Name: pyhbs
Version: 0.1.3
Summary: the simple Handlebars template compiler for Python 3
Home-page: http://github.com/anastue/pyhbs
Author: Anas Tuebingmah
Author-email: anas.tue@gmail.com
License: GNU
Platform: UNKNOWN
